galaxysled/__init__.py
galaxysled/functions.py
galaxysled/functions_mcmc.py
galaxysled/gmcs.py
galaxysled/resources/GMC_e24.csv
galaxysled/resources/GMC_e24_logM31_PDR.csv
galaxysled/resources/GMC_e24_logM31_XDR.csv
galaxysled/resources/GMC_e24_logM33_PDR.csv
galaxysled/resources/GMC_e24_logM33_XDR.csv
galaxysled/resources/GMC_e24_logM35_PDR.csv
galaxysled/resources/GMC_e24_logM35_XDR.csv
galaxysled/resources/GMC_e24_logM37_PDR.csv
galaxysled/resources/GMC_e24_logM37_XDR.csv
galaxysled/resources/GMC_e24_logM39_PDR.csv
galaxysled/resources/GMC_e24_logM39_XDR.csv
galaxysled/resources/GMC_e24_logM41_PDR.csv
galaxysled/resources/GMC_e24_logM41_XDR.csv
galaxysled/resources/GMC_e24_logM43_PDR.csv
galaxysled/resources/GMC_e24_logM43_XDR.csv
galaxysled/resources/GMC_e24_logM45_PDR.csv
galaxysled/resources/GMC_e24_logM45_XDR.csv
galaxysled/resources/GMC_e24_logM47_PDR.csv
galaxysled/resources/GMC_e24_logM47_XDR.csv
galaxysled/resources/GMC_e24_logM49_PDR.csv
galaxysled/resources/GMC_e24_logM49_XDR.csv
galaxysled/resources/GMC_e24_logM51_PDR.csv
galaxysled/resources/GMC_e24_logM51_XDR.csv
galaxysled/resources/GMC_e24_logM53_PDR.csv
galaxysled/resources/GMC_e24_logM53_XDR.csv
galaxysled/resources/GMC_e24_logM55_PDR.csv
galaxysled/resources/GMC_e24_logM55_XDR.csv
galaxysled/resources/GMC_e24_logM57_PDR.csv
galaxysled/resources/GMC_e24_logM57_XDR.csv
galaxysled/resources/GMC_e24_logM59_PDR.csv
galaxysled/resources/GMC_e24_logM59_XDR.csv
galaxysled/resources/GMC_f24.csv
galaxysled/resources/GMC_f24_logM31_PDR.csv
galaxysled/resources/GMC_f24_logM31_XDR.csv
galaxysled/resources/GMC_f24_logM33_PDR.csv
galaxysled/resources/GMC_f24_logM33_XDR.csv
galaxysled/resources/GMC_f24_logM35_PDR.csv
galaxysled/resources/GMC_f24_logM35_XDR.csv
galaxysled/resources/GMC_f24_logM37_PDR.csv
galaxysled/resources/GMC_f24_logM37_XDR.csv
galaxysled/resources/GMC_f24_logM39_PDR.csv
galaxysled/resources/GMC_f24_logM39_XDR.csv
galaxysled/resources/GMC_f24_logM41_PDR.csv
galaxysled-0.1.7.dist-info/LICENSE
galaxysled-0.1.7.dist-info/METADATA
galaxysled-0.1.7.dist-info/WHEEL
galaxysled-0.1.7.dist-info/top_level.txt
galaxysled-0.1.7.dist-info/RECORD
