Metadata-Version: 2.1
Name: galaxysled
Version: 0.1.7
Summary: A code to reproduce and fit a galaxy CO SLED
Home-page: https://github.com/federicoesposito/galaxySLED
Author: Federico Esposito
Author-email: Federico Esposito <federico.esposito7@unibo.it>
Project-URL: Homepage, https://github.com/federicoesposito/galaxySLED
Project-URL: Issues, https://github.com/federicoesposito/galaxySLED/issues
Classifier: Programming Language :: Python :: 3
Classifier: License :: OSI Approved :: GNU General Public License v3 (GPLv3)
Classifier: Operating System :: OS Independent
Requires-Python: >=3.6, <4
License-File: LICENSE
Requires-Dist: anyio >=3.6.2
Requires-Dist: argon2-cffi >=21.3.0
Requires-Dist: argon2-cffi-bindings >=21.2.0
Requires-Dist: async-generator >=1.10
Requires-Dist: attrs >=22.2.0
Requires-Dist: Babel >=2.11.0
Requires-Dist: backcall >=0.2.0
Requires-Dist: bash-kernel >=0.9.3
Requires-Dist: bleach >=4.1.0
Requires-Dist: certifi >=2024.8.30
Requires-Dist: cffi >=1.15.1
Requires-Dist: charset-normalizer >=2.0.12
Requires-Dist: comm >=0.1.4
Requires-Dist: contextvars >=2.4
Requires-Dist: corner >=2.2.1
Requires-Dist: cycler >=0.11.0
Requires-Dist: decorator >=5.1.1
Requires-Dist: defusedxml >=0.7.1
Requires-Dist: emcee >=3.1.6
Requires-Dist: entrypoints >=0.4
Requires-Dist: h5py >=3.1.0
Requires-Dist: idna >=3.8
Requires-Dist: immutables >=0.19
Requires-Dist: importlib-metadata >=4.8.3
Requires-Dist: importlib-resources >=5.4.0
Requires-Dist: ipykernel >=5.5.6
Requires-Dist: ipython >=7.16.3
Requires-Dist: ipython-genutils >=0.2.0
Requires-Dist: ipywidgets >=7.8.4
Requires-Dist: jedi >=0.17.2
Requires-Dist: Jinja2 >=3.0.3
Requires-Dist: joblib >=1.1.1
Requires-Dist: json5 >=0.9.16
Requires-Dist: jsonschema >=3.2.0
Requires-Dist: jupyter >=1.1.1
Requires-Dist: jupyter-client >=7.1.2
Requires-Dist: jupyter-console >=6.4.3
Requires-Dist: jupyter-core >=4.9.2
Requires-Dist: jupyter-server >=1.13.1
Requires-Dist: jupyterlab >=3.2.9
Requires-Dist: jupyterlab-pygments >=0.1.2
Requires-Dist: jupyterlab-server >=2.10.3
Requires-Dist: jupyterlab-widgets >=1.1.10
Requires-Dist: kiwisolver >=1.3.1
Requires-Dist: MarkupSafe >=2.0.1
Requires-Dist: matplotlib >=3.3.4
Requires-Dist: mistune >=0.8.4
Requires-Dist: nbclassic >=0.3.5
Requires-Dist: nbclient >=0.5.9
Requires-Dist: nbconvert >=6.0.7
Requires-Dist: nbformat >=5.1.3
Requires-Dist: nest-asyncio >=1.6.0
Requires-Dist: notebook >=6.4.10
Requires-Dist: numpy >=1.19.5
Requires-Dist: packaging >=21.3
Requires-Dist: pandas >=1.1.5
Requires-Dist: pandocfilters >=1.5.1
Requires-Dist: parso >=0.7.1
Requires-Dist: pexpect >=4.9.0
Requires-Dist: pickleshare >=0.7.5
Requires-Dist: Pillow >=8.4.0
Requires-Dist: prometheus-client >=0.17.1
Requires-Dist: prompt-toolkit >=3.0.36
Requires-Dist: ptyprocess >=0.7.0
Requires-Dist: pycparser >=2.21
Requires-Dist: Pygments >=2.14.0
Requires-Dist: pyparsing >=3.0.7
Requires-Dist: pyrsistent >=0.18.0
Requires-Dist: python-dateutil >=2.9.0.post0
Requires-Dist: pytz >=2024.1
Requires-Dist: pyzmq >=25.1.2
Requires-Dist: requests >=2.27.1
Requires-Dist: scipy >=1.5.4
Requires-Dist: Send2Trash >=1.8.3
Requires-Dist: setuptools >=59.6.0
Requires-Dist: setuptools-scm >=6.4.2
Requires-Dist: six >=1.16.0
Requires-Dist: sniffio >=1.2.0
Requires-Dist: terminado >=0.12.1
Requires-Dist: testpath >=0.6.0
Requires-Dist: tomli >=1.2.3
Requires-Dist: tornado >=6.1
Requires-Dist: tqdm >=4.64.1
Requires-Dist: traitlets >=4.3.3
Requires-Dist: typing-extensions >=4.1.1
Requires-Dist: urllib3 >=1.26.20
Requires-Dist: wcwidth >=0.2.13
Requires-Dist: webencodings >=0.5.1
Requires-Dist: websocket-client >=1.3.1
Requires-Dist: widgetsnbextension >=3.6.9
Requires-Dist: zipp >=3.6.0
